dask_cassandra_loader/__init__.py
dask_cassandra_loader/__version__.py
dask_cassandra_loader/loader.py
dask_cassandra_loader-1.1.0.dist-info/DESCRIPTION.rst
dask_cassandra_loader-1.1.0.dist-info/METADATA
dask_cassandra_loader-1.1.0.dist-info/RECORD
dask_cassandra_loader-1.1.0.dist-info/WHEEL
dask_cassandra_loader-1.1.0.dist-info/metadata.json
dask_cassandra_loader-1.1.0.dist-info/top_level.txt
