Metadata-Version: 2.0
Name: dask-cassandra-loader
Version: 1.1.0
Summary: A data loader which loads data from a Cassandra table into a Dask dataframe. It allows partition elimination,
Home-page: https://github.com/NLeSC/dask-cassandra-loader
Author: Romulo Goncalves
Author-email: romulopergon@gmail.com
Maintainer: Stefan Verhoeven
Maintainer-email: s.verhoeven@esciencecenter.nl
License: Apache Software License 2.0
Keywords: dask_cassandra_loader
Platform: UNKNOWN
Classifier: Development Status :: 2 - Pre-Alpha
Classifier: Intended Audience :: Developers
Classifier: License :: OSI Approved :: Apache Software License
Classifier: Natural Language :: English
Classifier: Programming Language :: Python :: 3
Classifier: Programming Language :: Python :: 3.6
Classifier: Programming Language :: Python :: 3.7
Classifier: Programming Language :: Python :: 3.8
Provides-Extra: dev
Requires-Dist: cassandra-driver
Requires-Dist: dask
Requires-Dist: distributed
Requires-Dist: fsspec
Requires-Dist: pandas
Requires-Dist: sqlalchemy
Provides-Extra: dev
Requires-Dist: prospector[with_pyroma]; extra == 'dev'
Requires-Dist: isort; extra == 'dev'
